{"timestamp":"2026-01-03T01:50:43.0762946+01:00","gameRunning":true,"properties":{"Speed":null,"SpeedKmh":null,"SpeedMph":null,"TrainLatitude":null,"TrainLongitude":null,"Altitude":null,"Heading":null,"Throttle":0.0,"Brake":0.0,"Direction":null,"CurrentTrackSpeedLimit":null,"Gradient":null,"TrackGrade":null,"Acceleration":null,"RPM":null,"Ammeter":null,"AmmeterBar":null,"DynamicBrake":null,"VirtualDynamicBrake":null,"TractiveEffort":null,"AirBrakePipePressurePSI":null,"AirBrakePipePressureBAR":null,"LocoBrakeCylinderPressurePSI":null,"LocoBrakeCylinderPressureBAR":null,"TrainBrakeCylinderPressurePSI":null,"TrainBrakeCylinderPressureBAR":null,"MainReservoirPressurePSI":null,"MainReservoirPressureBAR":null,"EqReservoirPressurePSI":null,"AuxReservoirPressure":null,"BrakePipePressureTailEnd":null,"AWS":null,"AWSWarnCount":null,"AWSReset":null,"EmergencyBrake":null,"HandBrake":null,"Sifa":null,"SifaAlarm":null,"SifaReset":null,"Startup":null,"VirtualStartup":null,"StartupSwitch":null,"EngineStop":null,"EngineStart":null,"CompressorState":null,"FuelLevel":null,"IsInTunnel":null,"Time":null,"TimeOfDayHours":null,"TimeOfDayMinutes":null,"TimeOfDaySeconds":null,"DistanceTravelled":null,"LocoProvider":null,"LocoEngineName":null,"LocoProduct":null,"Horn":null,"Bell":null,"Sander":null,"Wipers":null,"Headlights":null,"CabLight":null,"InstrumentLights":null,"StepLights":null,"NumberLights":null,"DoorsOpenCloseLeft":null,"DoorsOpenCloseRight":null,"WindowLeft":null,"WindowRight":null,"PCSstate":null,"BrakeDifficulty":null,"DrivingMode":null,"DisableBrakeNotches":null}}